pyembed_rst-1.1.0-py2.7-nspkg.pth
pyembed_rst-1.1.0.dist-info/metadata.json
pyembed_rst-1.1.0.dist-info/top_level.txt
pyembed_rst-1.1.0.dist-info/METADATA
pyembed_rst-1.1.0.dist-info/RECORD
pyembed_rst-1.1.0.dist-info/WHEEL
pyembed_rst-1.1.0.dist-info/DESCRIPTION.rst
pyembed_rst-1.1.0.dist-info/namespace_packages.txt
pyembed/rst/handler.py
pyembed/rst/__init__.py
