Metadata-Version: 2.0
Name: pyembed-rst
Version: 1.1.0
Summary: Python reStructuredText directive for embedding content using OEmbed
Home-page: http://pyembed.github.io
Author: Matt Thomson
Author-email: mattjohnthomson@gmail.com
License: Copyright (c) 2014 Matt Thomson
Requires-Dist: pyembed
Requires-Dist: docutils
